pulumi_linkerd_link
