Metadata-Version: 2.1
Name: pulumi-linkerd-link
Version: 0.0.7
Summary: A Pulumi package for linking k8s clusters with linkerd.
Home-page: UNKNOWN
License: Apache-2.0
Project-URL: Repository, https://github.com/antifuchs/pulumi-linkerd-link
Platform: UNKNOWN
